wordstream/__init__.py
wordstream/api.py
wordstream/dispatcher.py
wordstream/dissociate.py
wordstream/factory.py
wordstream/handlers.py
wordstream/main.py
wordstream-0.1.3.dist-info/METADATA
wordstream-0.1.3.dist-info/WHEEL
wordstream-0.1.3.dist-info/entry_points.txt
wordstream-0.1.3.dist-info/top_level.txt
wordstream-0.1.3.dist-info/RECORD
