Metadata-Version: 2.1
Name: wordstream
Version: 0.1.3
Summary: word streamer; conversational and dissociatively play with text with a command line and web interface
Home-page: http://k0s.org/hg/wordstream
Author: Jeff Hammel
Author-email: k0scist@gmail.com
License: GPL
Platform: UNKNOWN
Requires-Dist: Paste
Requires-Dist: PasteScript
Requires-Dist: WebOb
Requires-Dist: genshi
